leap/__init__.py
leap/api_client.py
leap/api_response.py
leap/apis/__init__.py
leap/apis/path_to_api.py
leap/apis/paths/__init__.py
leap/apis/paths/api_v1_images_models_model_id_inferences.py
leap/apis/paths/api_v1_images_models_model_id_inferences_inference_id.py
leap/apis/paths/api_v1_music.py
leap/apis/paths/api_v1_music_inference_id.py
leap/apis/paths/api_v2_images_models.py
leap/apis/paths/api_v2_images_models_model_id.py
leap/apis/paths/api_v2_images_models_new.py
leap/apis/tag_to_api.py
leap/apis/tags/__init__.py
leap/apis/tags/image_models_api.py
leap/apis/tags/images_api.py
leap/apis/tags/music_api.py
leap/client.py
leap/client.pyi
leap/client_custom.py
leap/configuration.py
leap/exceptions.py
leap/exceptions_base.py
leap/model/__init__.py
leap/model/create_and_train_model_dto.py
leap/model/create_and_train_model_dto.pyi
leap/model/create_and_train_model_dto_image_sample_files.py
leap/model/create_and_train_model_dto_image_sample_files.pyi
leap/model/create_and_train_model_dto_image_sample_urls.py
leap/model/create_and_train_model_dto_image_sample_urls.pyi
leap/model/create_inference_dto.py
leap/model/create_inference_dto.pyi
leap/model/create_musicgen_inference_dto.py
leap/model/create_musicgen_inference_dto.pyi
leap/model/inference_entity.py
leap/model/inference_entity.pyi
leap/model/inference_image_entity.py
leap/model/inference_image_entity.pyi
leap/model/inferences_controller_find_all_response.py
leap/model/inferences_controller_find_all_response.pyi
leap/model/list_models_v2_response.py
leap/model/list_models_v2_response.pyi
leap/model/model_v2_entity.py
leap/model/model_v2_entity.pyi
leap/model/model_v2_entity_image_samples.py
leap/model/model_v2_entity_image_samples.pyi
leap/model/music_controller_find_all_audio_response.py
leap/model/music_controller_find_all_audio_response.pyi
leap/model/musicgen_inference_entity.py
leap/model/musicgen_inference_entity.pyi
leap/models/__init__.py
leap/paths/__init__.py
leap_python_sdk-1.1.4.dist-info/LICENSE
leap_python_sdk-1.1.4.dist-info/METADATA
leap_python_sdk-1.1.4.dist-info/WHEEL
leap_python_sdk-1.1.4.dist-info/RECORD
